setup.cfg
setup.py
legs/__init__.py
legs/__main__.py
legs/automata.py
legs/codepoints.py
legs/rules.py
legs/swift.py
legs.egg-info/PKG-INFO
legs.egg-info/SOURCES.txt
legs.egg-info/dependency_links.txt
legs.egg-info/entry_points.txt
legs.egg-info/requires.txt
legs.egg-info/top_level.txt