Metadata-Version: 1.1
Name: legs
Version: 0.0.0
Summary: A lexical analyzer generator.
Home-page: https://github.com/gwk/legs
Author: George King
Author-email: george.w.king@gmail.com
License: CC0
Keywords: testing
Platform: UNKNOWN
Classifier: Development Status :: 3 - Alpha
Classifier: Environment :: Console
Classifier: Intended Audience :: Developers
Classifier: License :: CC0 1.0 Universal (CC0 1.0) Public Domain Dedication
Classifier: Programming Language :: Python :: 3 :: Only
